{
	"$schema": "https://inlang.com/schema/marketplace-manifest",
	"id": "library.inlang.paraglideJs",
	"icon": "./assets/paraglideNoBg.png",
	"gallery": [
		"./assets/og.png",
		"./assets/marketplace/paraglide-gallery/paraglide-gallery-image-1.jpg",
		"./assets/marketplace/paraglide-gallery/paraglide-gallery-image-2.jpg",
		"./assets/marketplace/paraglide-gallery/paraglide-gallery-image-3.jpg",
		"./assets/marketplace/paraglide-gallery/paraglide-gallery-image-4.jpg"
	],
	"displayName": {
		"en": "Paraglide JS"
	},
	"description": {
		"en": "Simple, adaptable and tiny i18n library that integrates with any framework"
	},
	"pages": {
		"": {
			"/": "./docs/introduction.md",
			"/comparison": "./docs/comparison.md",
			"/benchmark": "./benchmark/README.md",
			"/changelog": "./CHANGELOG.md"
		},
		"Getting Started": {
			"/sveltekit": "./examples/sveltekit/README.md",
			"/tanstack-router": "https://github.com/TanStack/router/tree/main/examples/react/i18n-paraglide",
			"/tanstack-start": "https://github.com/TanStack/router/tree/main/examples/react/start-i18n-paraglide",
			"/react-router": "./examples/react-router/README.md",
			"/next-js": "./docs/getting-started/next-js.md",
			"/astro": "./examples/astro/README.md",
			"/vite": "./examples/vite/README.md",
			"/vanilla-js-ts": "./docs/getting-started/vanilla-js-ts.md"
		},
		"Usage": {
			"/basics": "./docs/basics.md",
			"/message-keys": "./docs/message-keys.md",
			"/strategy": "./docs/strategy.md",
			"/variants": "./docs/variants.md",
			"/file-formats": "./docs/file-formats.md",
			"/multi-tenancy": "./docs/multi-tenancy.md",
			"/server-side-rendering": "./docs/server-side-rendering.md",
			"/compiling-messages": "./docs/compiling-messages.md",
			"/incremental-migration": "./examples/incremental-migration/README.md"
		},
		"Reference": {
			"/architecture": "./docs/architecture.md",
			"/compiler-options": "./docs-api/compiler-options.md",
			"/runtime": "./docs-api/runtime/type/-internal-.md",
			"/server": "./docs-api/server/type/-internal-.md",
			"/errors": "./docs/errors.md"
		},
		"Ecosystem": {
			"Sherlock VSCode extension": "/m/r7kp499g/app-inlang-ideExtension",
			"CLI for automation": "/m/2qj2w8pu/app-inlang-cli",
			"Fink web editor": "/m/tdozzpar/app-inlang-finkLocalizationEditor"
		}
	},
	"keywords": [
		"paraglide js",
		"libraries",
		"apps",
		"website",
		"developer",
		"paraglide",
		"i18n",
		"library",
		"localization",
		"sdk",
		"sdk-js",
		"svelte",
		"react",
		"nextjs",
		"remix",
		"vue",
		"astro",
		"javascript",
		"solid",
		"typescript",
		"react router",
		"inlang"
	],
	"recommends": ["m/reootnfj", "m/632iow21", "m/r7kp499g", "m/2qj2w8pu"],
	"pricing": "free",
	"publisherName": "inlang",
	"publisherIcon": "https://inlang.com/favicon/safari-pinned-tab.svg",
	"license": "MIT"
}
